fireblocks_cli/__init__.py
fireblocks_cli/__main__.py
fireblocks_cli/config.py
fireblocks_cli/crypto.py
fireblocks_cli/main.py
fireblocks_cli/auth/__init__.py
fireblocks_cli/auth/base.py
fireblocks_cli/auth/factory.py
fireblocks_cli/auth/file_provider.py
fireblocks_cli/auth/vault_provider.py
fireblocks_cli/commands/configure.py
fireblocks_cli/commands/profile_debug.py
fireblocks_cli/types/__init__.py
fireblocks_cli/types/profile_config.py
fireblocks_cli/utils/__init__.py
fireblocks_cli/utils/profile.py
fireblocks_cli/utils/toml.py
fireblocks_cli-0.1.10.dist-info/licenses/LICENSE
fireblocks_cli-0.1.10.dist-info/METADATA
fireblocks_cli-0.1.10.dist-info/WHEEL
fireblocks_cli-0.1.10.dist-info/entry_points.txt
fireblocks_cli-0.1.10.dist-info/top_level.txt
fireblocks_cli-0.1.10.dist-info/RECORD
