Metadata-Version: 2.4
Name: fireblocks-cli
Version: 0.1.10
Summary: An unofficial CLI for managing Fireblocks services.
Author-email: Kamon Shohei <cameong@stir.network>
Requires-Python: <3.14,>=3.11
License-File: LICENSE
Requires-Dist: typer[all]>0.15.0
Requires-Dist: toml>0.10.0
Requires-Dist: tomlkit<0.14.0,>=0.13.2
Requires-Dist: fireblocks-sdk<3.0.0,>=2.16.1
Provides-Extra: dev
Requires-Dist: mypy>=1.15.0; extra == "dev"
Requires-Dist: black<26.0.0,>=25.1.0; extra == "dev"
Requires-Dist: pyinstaller>=6.13.0; extra == "dev"
Requires-Dist: black>=25.1.0; extra == "dev"
Requires-Dist: reuse>=5.0.2; (python_version >= "3.9" and python_version < "4.0") and extra == "dev"
Requires-Dist: pre-commit>=4.2.0; extra == "dev"
Requires-Dist: build>=1.2.2.post1; extra == "dev"
Requires-Dist: twine>=6.1.0; extra == "dev"
Requires-Dist: pytest>=8.3.5; extra == "dev"
Requires-Dist: types-toml>=0.10.8.20240310; extra == "dev"
Dynamic: license-file
